ApTop/ApacheStatus.py
ApTop/AptopCurses.py
ApTop/__init__.py
aptop-0.4.0.data/scripts/aptop.py
aptop-0.4.0.dist-info/LICENSE
aptop-0.4.0.dist-info/METADATA
aptop-0.4.0.dist-info/WHEEL
aptop-0.4.0.dist-info/top_level.txt
aptop-0.4.0.dist-info/RECORD
