Metadata-Version: 2.1
Name: aptop
Version: 0.4.0
Summary: ApTop is top like clone for Apache
Home-page: https://github.com/btoic/aptop
Author: Branko Toic
Author-email: branko.toic@gmail.com
License: GPLv2
Platform: unix
Provides: ApTop
License-File: LICENSE
Requires-Dist: lxml
